vecnom/__init__.py
vecnom/client.py
vecnom-0.2.7.2.dist-info/METADATA
vecnom-0.2.7.2.dist-info/WHEEL
vecnom-0.2.7.2.dist-info/RECORD
